pandora/__init__.py
pandora/conftest.py
pandora/test_main.py
pandora/ai/appliTools.py
pandora/config/config.py
pandora/drivers/__init__.py
pandora/drivers/common_actions.py
pandora/drivers/web_browser.py
pandora/integrations/__init__.py
pandora/integrations/ado.py
pandora/integrations/registry.py
pandora/integrations/pytest_html_reporter/__init__.py
pandora/integrations/pytest_html_reporter/plugin.py
pandora/integrations/pytest_html_reporter/template.py
pandora/integrations/pytest_html_reporter/time_converter.py
pandora/reports/__init__.py
pandora/testdata/__init__.py
pandora/tests/__init__.py
pandora/tests/test_assertion.py
pandora/tests/test_file_helper.py
pandora/tests/test_helper.py
pandora/tests/test_json_utils.py
pandora/tests/test_mark_demo.py
pandora/tests/test_registry.py
pandora/tests/test_screenshot_helper.py
pandora/tests/test_send_email.py
pandora/tests/test_settings_loader.py
pandora/tests/test_web_browser.py
pandora/utils/__init__.py
pandora/utils/assertion.py
pandora/utils/email.py
pandora/utils/file_helper.py
pandora/utils/helper.py
pandora/utils/html_report_helper.py
pandora/utils/json_utils.py
pandora/utils/screenshot_helper.py
pandora/utils/settings_loader.py
pandora/utils/testdata_handler.py
pandora_common_package-0.4.0.dist-info/METADATA
pandora_common_package-0.4.0.dist-info/WHEEL
pandora_common_package-0.4.0.dist-info/top_level.txt
pandora_common_package-0.4.0.dist-info/RECORD
