Metadata-Version: 2.4
Name: Pandora_Common_Package
Version: 0.4.0
Summary: Common utils for different projects
Classifier: Programming Language :: Python :: 3
Classifier: Operating System :: OS Independent
Requires-Python: >=3.9
Requires-Dist: pytest
Requires-Dist: requests
Requires-Dist: PyYAML
Requires-Dist: pytest-html
Requires-Dist: allure-pytest
Requires-Dist: pytest-xdist
Requires-Dist: jmespath
Requires-Dist: webdriver-manager
Requires-Dist: selenium
Requires-Dist: PyJWT
Requires-Dist: loguru
Requires-Dist: pyautogui
Requires-Dist: jsonschema
Requires-Dist: deepdiff
Requires-Dist: responses
Requires-Dist: test-soft-assertion-tool
